MANIFEST.in
setup.py
python/jittor_offline/__init__.py
python/jittor_offline/cub-1.11.0.tgz
python/jittor_offline/cutt-1.2.zip
python/jittor_offline/dnnl_lnx_2.2.0_cpu_gomp.tgz
python/jittor_offline/dnnl_lnx_2.2.0_cpu_gomp_aarch64.tgz
python/jittor_offline/nccl.tgz
python/jittor_offline/t10k-images-idx3-ubyte.gz
python/jittor_offline/t10k-labels-idx1-ubyte.gz
python/jittor_offline/train-images-idx3-ubyte.gz
python/jittor_offline/train-labels-idx1-ubyte.gz
python/jittor_offline.egg-info/PKG-INFO
python/jittor_offline.egg-info/SOURCES.txt
python/jittor_offline.egg-info/dependency_links.txt
python/jittor_offline.egg-info/requires.txt
python/jittor_offline.egg-info/top_level.txt
python/jittor_offline/__pycache__/__init__.cpython-310.pyc